README.txt
setup.py
Products/__init__.py
Products.PloneFilesZip.egg-info/PKG-INFO
Products.PloneFilesZip.egg-info/SOURCES.txt
Products.PloneFilesZip.egg-info/dependency_links.txt
Products.PloneFilesZip.egg-info/entry_points.txt
Products.PloneFilesZip.egg-info/namespace_packages.txt
Products.PloneFilesZip.egg-info/not-zip-safe
Products.PloneFilesZip.egg-info/requires.txt
Products.PloneFilesZip.egg-info/top_level.txt
Products/PloneFilesZip/ABOUT
Products/PloneFilesZip/CHANGES
Products/PloneFilesZip/DcmesXml.py
Products/PloneFilesZip/LICENSE
Products/PloneFilesZip/PloneFilesZipTool.py
Products/PloneFilesZip/README.txt
Products/PloneFilesZip/TODO
Products/PloneFilesZip/__init__.py
Products/PloneFilesZip/config.py
Products/PloneFilesZip/fileszip_icon.png
Products/PloneFilesZip/interfaces.py
Products/PloneFilesZip/policies.py
Products/PloneFilesZip/product.txt
Products/PloneFilesZip/registry.py
Products/PloneFilesZip/retrievers.py
Products/PloneFilesZip/tool.gif
Products/PloneFilesZip/version.txt
Products/PloneFilesZip/Extensions/Install.py
Products/PloneFilesZip/Extensions/__init__.py
Products/PloneFilesZip/doc/FAQ
Products/PloneFilesZip/doc/SCREENSHOTS
Products/PloneFilesZip/doc/before_download.png
Products/PloneFilesZip/doc/folder_view.png
Products/PloneFilesZip/doc/icon.png
Products/PloneFilesZip/i18n/plonefileszip-fr.po
Products/PloneFilesZip/i18n/plonefileszip-pt-br.po
Products/PloneFilesZip/i18n/plonefileszip.pot
Products/PloneFilesZip/i18n/plonefileszip_plone-fr.po
Products/PloneFilesZip/i18n/plonefileszip_plone-pt-br.po
Products/PloneFilesZip/i18n/plonefileszip_plone.pot
Products/PloneFilesZip/skins/files_zip/README.txt
Products/PloneFilesZip/skins/files_zip/files_zip_form.pt
Products/PloneFilesZip/skins/files_zip/files_zip_form.pt.metadata
Products/PloneFilesZip/skins/files_zip/files_zip_icon.png
Products/PloneFilesZip/skins/files_zip/files_zip_icon.png.metadata
Products/PloneFilesZip/skins/files_zip/prefs_files_zip_form.cpt
Products/PloneFilesZip/skins/files_zip/prefs_files_zip_form.cpt.metadata
Products/PloneFilesZip/skins/files_zip/prefs_files_zip_form_set.cpy
Products/PloneFilesZip/skins/files_zip/prefs_files_zip_form_validate.vpy
Products/PloneFilesZip/tests/PloneFilesZipTestCase.py
Products/PloneFilesZip/tests/README.txt
Products/PloneFilesZip/tests/__init__.py
Products/PloneFilesZip/tests/common.py
