Metadata-Version: 1.0
Name: Products.PloneFilesZip
Version: 1.2.0b1
Summary: PloneFilesZip provides a tool that let users download all files from a folder (recursively) in a ZIP archive
Home-page: http://pypi.python.org/pypi/Products.PloneFilesZip
Author: Gilles Lenfant
Author-email: gilles.lenfant@alterway.fr
License: GPL
Keywords: plone files archives
Platform: UNKNOWN
Classifier: Programming Language :: Python
Classifier: Framework :: Plone
